Metadata-Version: 2.1
Name: djangorestframework-jwt-v2
Version: 1.11.2
Summary: JSON Web Token based authentication for Django REST framework
Home-page: https://github.com/edmon1024/djangorestframework-jwt-v2
Author: Jose Padilla
Author-email: jpadilla@getblimp.com
License: MIT
Classifier: Development Status :: 5 - Production/Stable
Classifier: Environment :: Web Environment
Classifier: Framework :: Django
Classifier: Intended Audience :: Developers
Classifier: License :: OSI Approved :: MIT License
Classifier: Operating System :: OS Independent
Classifier: Programming Language :: Python
Classifier: Programming Language :: Python :: 2
Classifier: Programming Language :: Python :: 2.7
Classifier: Programming Language :: Python :: 3
Classifier: Programming Language :: Python :: 3.3
Classifier: Programming Language :: Python :: 3.4
Classifier: Programming Language :: Python :: 3.5
Classifier: Topic :: Internet :: WWW/HTTP
License-File: LICENSE
Requires-Dist: PyJWT <2.0.0,>=1.5.2
